Ejercicio2/Ejercicio2.v
//Juan Eliseo Lux Cajas
//Lab9
//Ejecicio 2

module ffd1 (input clk, reset, enable, d, output reg q);
    always @ (posedge clk or posedge reset)begin
        if (reset) begin
            q <= 1'b0;
        end
        else if (enable) begin
            q <= d;
        end
    end
endmodule


module fft(input wire clk, reset, enable, output wire Y);
    wire d;
    not (d, Y);
    ffd1 u(clk, reset, enable, d, Y);
endmodule

Ejercicio2/Ejercicio2_tb.v
//Juan Eliseo Lux Cajas
//Lab9
//Ejecicio 2 tb

module testbench();

reg clk, reset, enable, T;
wire salida;


fft f(clk, reset, enable,salida);


        always
            begin
                clk <= 0; reset <= 0; #1 clk <= 1; #1;
            end


    initial begin
        $display("----------------------------");
		$display("----------------------------");
        $display("----------FF T--------------");
        $display("clk | reset | enable | T  | salida");
        $monitor("%b  | %b  |    %b    | %b | %b ", clk,reset, enable, T, salida);
        clk = 0; reset = 0; enable = 0; T = 0;
     #1  reset = 1;
     #1  reset = 0;
     #2  enable = 1;
     #2  T = 1;
    end

   always
    #1  clk = ~clk;

   initial
        #25 $finish;

        initial begin
            $dumpfile("E2_tb.vcd");
            $dumpvars(0, testbench);
        end

        endmodule

Ejercicio2/E2_tb.vcd
$date
	Sat Oct 31 11:02:17 2020
$end
$version
	Icarus Verilog
$end
$timescale
	1ps
$end
$scope module testbench $end
$var wire 1 ! salida $end
$var reg 1 " T $end
$var reg 1 # clk $end
$var reg 1 $ enable $end
$var reg 1 % reset $end
$scope module f $end
$var wire 1 # clk $end
$var wire 1 & d $end
$var wire 1 $ enable $end
$var wire 1 % reset $end
$var wire 1 ! Y $end
$scope module u $end
$var wire 1 # clk $end
$var wire 1 & d $end
$var wire 1 $ enable $end
$var wire 1 % reset $end
$var reg 1 ! q $end
$upscope $end
$upscope $end
$upscope $end
$enddefinitions $end
#0
$dumpvars
x&
0%
0$
0#
0"
x!
$end
#1
1&
0!
1#
1%
#2
0#
0%
#3
1#
#4
0#
1$
#5
0&
1!
1#
#6
0#
1"
#7
1&
0!
1#
#8
0#
#9
0&
1!
1#
#10
0#
#11
1&
0!
1#
#12
0#
#13
0&
1!
1#
#14
0#
#15
1&
0!
1#
#16
0#
#17
0&
1!
1#
#18
0#
#19
1&
0!
1#
#20
0#
#21
0&
1!
1#
#22
0#
#23
1&
0!
1#
#24
0#
#25
0&
1!
1#
