Ejercicio4/Ejercicio4.v
//Juan Eliseo Lux Cajas
//Lab9
//Ejecicio 4

module bft(input enable, input [3:0]d, output logic [3:0]q);
	always @ (*)
		if (enable == 0)
			q <= 1'bz;
		else
			q <= d;
endmodule

Ejercicio4/Ejercicio4_tb.v
//Juan Eliseo Lux Cajas
//Lab9
//Ejecicio 4 Tb

module testbench();

reg enabled = 0;
reg [3:0]d;
output wire [3:0]q;

bft a(enabled, d, q);

initial begin
	   enabled=0; d=4'b0110;
	#2 enabled=1; d=4'b0001;
	#2 enabled=1; d=4'b0010;
	#2 enabled=1; d=4'b1011;
	#2 enabled=0; d=4'b0100;
	#2 enabled=1; d=4'b0001;
	#2 enabled=1; d=4'b0011;
	#2 enabled=0; d=4'b0101;
	#2 enabled=1; d=4'b1010;
end


initial
	#20 $finish;

initial begin
	$dumpfile("E4_tb.vcd");
	$dumpvars(0, testbench);
	end
endmodule

Ejercicio4/E4_tb.vcd
$date
	Sat Oct 31 11:03:27 2020
$end
$version
	Icarus Verilog
$end
$timescale
	1ps
$end
$scope module testbench $end
$var wire 4 ! q [3:0] $end
$var reg 4 " d [3:0] $end
$var reg 1 # enabled $end
$scope module a $end
$var wire 4 $ d [3:0] $end
$var wire 1 # enable $end
$var reg 4 % q [3:0] $end
$upscope $end
$upscope $end
$enddefinitions $end
#0
$dumpvars
b0z %
b110 $
0#
b110 "
b0z !
$end
#2
b1 !
b1 %
b1 "
b1 $
1#
#4
b10 !
b10 %
b10 "
b10 $
#6
b1011 !
b1011 %
b1011 "
b1011 $
#8
b0z !
b0z %
b100 "
b100 $
0#
#10
b1 !
b1 %
b1 "
b1 $
1#
#12
b11 !
b11 %
b11 "
b11 $
#14
b0z !
b0z %
b101 "
b101 $
0#
#16
b1010 !
b1010 %
b1010 "
b1010 $
1#
