Ejercicio1/Ejercicio1.v
//Juan Eliseo Lux Cajas
//Lab9
//Ejecicio 1

module updown(output  y1, output y2);
	assign y1 = 0;
	assign y2 = 1;
endmodule


module ffd1(input clk, input reset, input enable, input d, output logic salida);

	always @ (posedge clk, posedge reset)
		if (reset)
			salida  <= 1'b0;
		else if (enable)
			salida <= d;
endmodule

module ffd2(input clk, input reset, input enable, input [1:0]d, output logic [1:0]salida);

	always @ (posedge clk, posedge reset)
		if (reset)
			salida <= 2'b0;
		else if (enable)
			salida <= d;
endmodule

module ffd4(input clk, input reset, input enable, input [3:0]d, output logic [3:0]salida);

	always @ (posedge clk, posedge reset)
		if (reset)
			salida <= 4'b0;
		else if (enable)
			salida <= d;
endmodule

Ejercicio1/Ejercicio1_tb.v
//Juan Eliseo Lux Cajas
//Lab9
//Ejecicio 1 Tb
module testbench();

reg clk = 0;
reg reset = 0;
reg enable = 0;
reg d1;
reg [1:0]d2;
reg [3:0]d4;
output wire q1;
output wire[1:0]q2;
output wire[3:0]q4;

ffd1 f1(clk, reset, enable, d1, q1);
ffd2 f2(clk, reset, enable, d2, q2);
ffd4 f3(clk, reset, enable, d4, q4);

initial begin
     #1	d1=1'b1; d2=2'b10;  d4=4'b1010; enable=1;
     #1 d1=1'b0; d2=2'b00;  d4=4'b1110; enable=1;
	 #1 reset=1;
     #1 d1=1'b1; d2=2'b01;  d4=4'b1011; enable=0;
     #1 d1=1'b1; d2=2'b11;  d4=4'b1100; enable=1;
	 #3 reset=0;
     #1 d1=1'b0; d2=2'b10;  d4=4'b1111; enable=1;
     #1 d1=1'b1; d2=2'b11;  d4=4'b0001; enable=0;

     #1 d1=1'b0; d2=2'b11;  d4=4'b1110; enable=0;
     #1 d1=1'b1; d2=2'b10;  d4=4'b1101; enable=1;

end

always@(*)begin
	#1 clk = ~clk;
end
always@(*)begin
	#1 clk = ~clk;
end

initial
	#15 $finish;

initial begin
	$dumpfile("E1_tb.vcd");
	$dumpvars(0, testbench);
	end
endmodule

Ejercicio1/E1_tb.vcd
$date
	Sat Oct 31 10:54:11 2020
$end
$version
	Icarus Verilog
$end
$timescale
	1ps
$end
$scope module testbench $end
$var wire 4 ! q4 [3:0] $end
$var wire 2 " q2 [1:0] $end
$var wire 1 # q1 $end
$var reg 1 $ clk $end
$var reg 1 % d1 $end
$var reg 2 & d2 [1:0] $end
$var reg 4 ' d4 [3:0] $end
$var reg 1 ( enable $end
$var reg 1 ) reset $end
$scope module f1 $end
$var wire 1 $ clk $end
$var wire 1 % d $end
$var wire 1 ( enable $end
$var wire 1 ) reset $end
$var reg 1 # salida $end
$upscope $end
$scope module f2 $end
$var wire 1 $ clk $end
$var wire 2 * d [1:0] $end
$var wire 1 ( enable $end
$var wire 1 ) reset $end
$var reg 2 + salida [1:0] $end
$upscope $end
$scope module f3 $end
$var wire 1 $ clk $end
$var wire 4 , d [3:0] $end
$var wire 1 ( enable $end
$var wire 1 ) reset $end
$var reg 4 - salida [3:0] $end
$upscope $end
$upscope $end
$enddefinitions $end
#0
$dumpvars
bx -
bx ,
bx +
bx *
0)
0(
bx '
bx &
x%
0$
x#
bx "
bx !
$end
#1
1#
b10 "
b10 +
b1010 !
b1010 -
0$
1(
b1010 '
b1010 ,
b10 &
b10 *
1%
#2
b1110 !
b1110 -
b0 "
b0 +
0#
1$
b1110 '
b1110 ,
b0 &
b0 *
0%
#3
b0 !
b0 -
0$
1)
#4
1$
0(
b1011 '
b1011 ,
b1 &
b1 *
1%
#5
0$
1(
b1100 '
b1100 ,
b11 &
b11 *
#6
1$
#7
0$
#8
b1100 !
b1100 -
b11 "
b11 +
1#
1$
0)
#9
0$
b1111 '
b1111 ,
b10 &
b10 *
0%
#10
1$
0(
b1 '
b1 ,
b11 &
b11 *
1%
#11
0$
b1110 '
b1110 ,
0%
#12
b1101 !
b1101 -
b10 "
b10 +
1$
1(
b1101 '
b1101 ,
b10 &
b10 *
1%
