Ejercicio3/Ejercicio3.v
//Juan Eliseo Lux Cajas
//Lab9
//Ejecicio 3

module ffd(input wire clk, reset, enable, D, output reg Q);

    always @(posedge clk or posedge reset) begin
        if(reset)
            Q <= 0;
        else if (enable)
            Q <= D;
    end
endmodule

module ffjk(input wire clk, reset, enable, J, K, output wire Q);

    wire nQ, nK, aJ, aK, q;

    not(nQ, Q);
    not(nK, K);
    and(aJ, J, nQ);
    and(aK, nK, Q);
    or(q, aJ, aK);

		ffd U1(clk, reset, enable, q, Q);
endmodule

Ejercicio3/Ejercicio3_tb.v
//Juan Eliseo Lux Cajas
//Lab9
//Ejecicio 3

module testbench();

reg clk, reset, enable, J, K;
wire Q;

ffjk U1(clk, reset, enable, J, K, Q);

initial begin
     clk = 0; reset = 0; enable = 0; J = 0; K = 0;
    #2 reset = 0;
    #2 reset = 1;
    #2 reset = 0;
    #2 enable = 1; J = 1;
    #2 enable = 0;
    #2 enable = 1; J = 0;
    #2 K = 1;
    #2 J = 1; K = 0;
    #2 K = 1;
end

always
    #1 clk = ~clk;

initial
    #25 $finish;

initial begin
    $dumpfile("E3_tb.vcd");
    $dumpvars(0, testbench);
end

endmodule

Ejercicio3/E3_tb.vcd
$date
	Sat Oct 31 11:02:52 2020
$end
$version
	Icarus Verilog
$end
$timescale
	1ps
$end
$scope module testbench $end
$var wire 1 ! Q $end
$var reg 1 " J $end
$var reg 1 # K $end
$var reg 1 $ clk $end
$var reg 1 % enable $end
$var reg 1 & reset $end
$scope module U1 $end
$var wire 1 " J $end
$var wire 1 # K $end
$var wire 1 ' aJ $end
$var wire 1 ( aK $end
$var wire 1 $ clk $end
$var wire 1 % enable $end
$var wire 1 ) nK $end
$var wire 1 * nQ $end
$var wire 1 + q $end
$var wire 1 & reset $end
$var wire 1 ! Q $end
$scope module U1 $end
$var wire 1 + D $end
$var wire 1 $ clk $end
$var wire 1 % enable $end
$var wire 1 & reset $end
$var reg 1 ! Q $end
$upscope $end
$upscope $end
$upscope $end
$enddefinitions $end
#0
$dumpvars
x+
x*
1)
x(
0'
0&
0%
0$
0#
0"
x!
$end
#1
1$
#2
0$
#3
1$
#4
0+
0(
1*
0!
0$
1&
#5
1$
#6
0$
0&
#7
1$
#8
1+
1'
0$
1"
1%
#9
0'
1(
0*
1!
1$
#10
0$
0%
#11
1$
#12
0$
0"
1%
#13
1$
#14
0+
0(
0)
0$
1#
#15
1*
0!
1$
#16
1+
1)
1'
0$
0#
1"
#17
0'
1(
0*
1!
1$
#18
0+
0(
0)
0$
1#
#19
1+
1'
1*
0!
1$
#20
0$
#21
0+
0'
0*
1!
1$
#22
0$
#23
1+
1'
1*
0!
1$
#24
0$
#25
0+
0'
0*
1!
1$
